pollevbot/__init__.py
pollevbot/endpoints.py
pollevbot/main.py
pollevbot/pollbot.py
pollevbot-1.0.3.dist-info/LICENSE
pollevbot-1.0.3.dist-info/METADATA
pollevbot-1.0.3.dist-info/WHEEL
pollevbot-1.0.3.dist-info/top_level.txt
pollevbot-1.0.3.dist-info/RECORD
