Metadata-Version: 2.1
Name: pollevbot
Version: 1.0.3
Summary: A Python script that automatically responds to polls on PollEverywhere.
Home-page: https://github.com/danielqiang/pollevbot
Author: Daniel Qiang
Author-email: daniel_qiang@hotmail.com
License: UNKNOWN
Platform: UNKNOWN
Classifier: Development Status :: 3 - Alpha
Classifier: Intended Audience :: Developers
Classifier: License :: OSI Approved :: MIT License
Classifier: Programming Language :: Python :: 3
Classifier: Topic :: Software Development :: Libraries :: Python Modules
Requires-Python: >=3.7
Requires-Dist: requests
Requires-Dist: bs4
